{
    "attributes": {},
    "nodes": {
        "65cd1d6287f8470e9d1f544b": {
            "label": "Entity",
            "attributes": {
                "688d1b8eedf407bf697d4e5b": {
                    "key": "enum",
                    "value": "enum",
                    "options": {
                        "first": "first",
                        "second": "second",
                        "thrid": "thrid"
                    }
                },
                "99a086227f5acf22f0bf744e": {
                    "key": "id",
                    "value": "string"
                },
                "9ee1f533748cfee401f91489": {
                    "key": "name",
                    "value": "string",
                    "visibility": "show"
                },
                "c424aea20382947c47b143c1": {
                    "key": "title",
                    "value": "string",
                    "visibility": "show"
                },
                "eb1a39b875bf048f65c1ad51": {
                    "key": "number",
                    "value": "integer",
                    "visibility": "show"
                },
                "c6a28b251303d9a923ee67be": {
                    "key": "bool",
                    "value": "boolean",
                    "visibility": "show"
                },
                "318f477278d317b2328ad2fd": {
                    "key": "file",
                    "value": "file",
                    "visibility": "show"
                }
            },
            "shape": {
                "shape": "rectangle",
                "color": "",
                "defaultWidth": 0,
                "defaultHeight": 0,
                "customShape": "<div class=\"custom_node\">\n    <div class=\"type\"><%= type %></div>\n    <svg xmlns=\"http://www.w3.org/2000/svg\" preserveAspectRatio=\"none\" viewBox=\"0 0 100 100\" class=\"fill_parent\">\n        <rect x=\"0\" y=\"0\" width=\"100\" height=\"100\" fill=\"rgb(255, 255, 255)\" stroke=\"black\" stroke-width=\"2\"></rect>\n    </svg>\n    <div class=\"fill_parent\">\n        <div style=\"position: absolute; left: 50%; top: 50%; -webkit-transform: translateY(-50%) translateX(-50%)\" class=\"name center\"></div>\n    </div>\n</div>",
                "customAnchors": ""
            },
            "target": "04e7ae49df1d781508efb73b",
            "conditions": {},
            "conjunction": "AND"
        },
        "036d16d54e67f9d4511fb0e3": {
            "label": "Relationship",
            "attributes": {
                "ff4144623b46fa9d4f233696": {
                    "key": "name",
                    "value": "string",
                    "visibility": "show"
                },
                "99b9a9555ea2275accd9df6c": {
                    "key": "type",
                    "value": "string",
                    "visibility": "show"
                }
            },
            "shape": {
                "shape": "diamond",
                "color": "",
                "defaultWidth": 0,
                "defaultHeight": 0,
                "customShape": "<div class=\"custom_node\">\n    <div class=\"type\"><%= type %></div>\n    <svg xmlns=\"http://www.w3.org/2000/svg\" preserveAspectRatio=\"none\" viewBox=\"0 0 100 60\" class=\"fill_parent\">\n          <path stroke=\"black\" stroke-width=\"1\" fill=\"rgb(255, 255, 255)\" d=\"M15,0 L85,0 L100,30 L85,60 L15,60 L0,30 L15,0\"></path>\n    </svg>\n    <div class=\"fill_parent\">\n        <div style=\"position: absolute; left: 50%; top: 50%; -webkit-transform: translateY(-50%) translateX(-50%)\" class=\"name center\"><div class=\"single_value_attribute\">\n</div></div>\n    </div>\n</div>",
                "customAnchors": ""
            },
            "target": "f8a371547fdf952414aa1c49",
            "conditions": {},
            "conjunction": "AND"
        }
    },
    "edges": {
        "edae24842fc13742f4c7ef41": {
            "label": "Associations",
            "shape": {
                "arrow": "bidirassociation",
                "shape": "straight",
                "color": "",
                "overlay": "",
                "overlayPosition": "hidden",
                "overlayRotate": true
            },
            "relations": [
                {
                    "sourceTypes": [
                        "Entity"
                    ],
                    "targetTypes": [
                        "Relationship"
                    ]
                }
            ],
            "attributes": {
                "92a3c562ca6491404fc7518e": {
                    "key": "name",
                    "value": "string",
                    "position": "center"
                },
                "b76dc99013a1d7b4eaddcf1b": {
                    "key": "cardinality1",
                    "value": "string",
                    "position": "top"
                },
                "19bf1620df4136b8b8747958": {
                    "key": "bool",
                    "value": "boolean",
                    "position": "hidden"
                },
                "aa4a72389129c0dc9cc952c2": {
                    "key": "cardinality2",
                    "value": "string",
                    "position": "bottom"
                }
            },
            "target": "500ede69e2a7612a3d635d8e",
            "conditions": {},
            "conjunction": "AND"
        }
    },
    "id": "hiddenAttributes"
}